{ "city": "Montreal, QC", "time": 1401708910 
, "stations": [
{ "id": 0, "bikes": 1, "free": 29}
,{ "id": 1, "bikes": 14, "free": 8}
,{ "id": 2, "bikes": 10, "free": 5}
,{ "id": 3, "bikes": 35, "free": 6}
,{ "id": 4, "bikes": 0, "free": 15}
,{ "id": 5, "bikes": 0, "free": 23}
,{ "id": 6, "bikes": 19, "free": 16}
,{ "id": 7, "bikes": 6, "free": 17}
,{ "id": 8, "bikes": 5, "free": 38}
,{ "id": 9, "bikes": 13, "free": 2}
,{ "id": 10, "bikes": 14, "free": 34}
,{ "id": 11, "bikes": 2, "free": 28}
,{ "id": 12, "bikes": 2, "free": 29}
,{ "id": 13, "bikes": 7, "free": 20}
,{ "id": 14, "bikes": 6, "free": 5}
,{ "id": 15, "bikes": 1, "free": 18}
,{ "id": 16, "bikes": 3, "free": 20}
,{ "id": 17, "bikes": 13, "free": 2}
,{ "id": 18, "bikes": 6, "free": 29}
,{ "id": 19, "bikes": 7, "free": 8}
,{ "id": 20, "bikes": 2, "free": 21}
,{ "id": 21, "bikes": 39, "free": 33}
,{ "id": 22, "bikes": 5, "free": 10}
,{ "id": 23, "bikes": 11, "free": 4}
,{ "id": 24, "bikes": 5, "free": 10}
,{ "id": 25, "bikes": 11, "free": 30}
,{ "id": 26, "bikes": 16, "free": 6}
,{ "id": 27, "bikes": 17, "free": 24}
,{ "id": 28, "bikes": 1, "free": 42}
,{ "id": 29, "bikes": 0, "free": 15}
,{ "id": 30, "bikes": 3, "free": 20}
,{ "id": 31, "bikes": 5, "free": 18}
,{ "id": 32, "bikes": 10, "free": 13}
,{ "id": 33, "bikes": 3, "free": 27}
,{ "id": 34, "bikes": 12, "free": 11}
,{ "id": 35, "bikes": 5, "free": 14}
,{ "id": 36, "bikes": 8, "free": 6}
,{ "id": 37, "bikes": 5, "free": 26}
,{ "id": 38, "bikes": 6, "free": 21}
,{ "id": 39, "bikes": 10, "free": 2}
,{ "id": 40, "bikes": 18, "free": 13}
,{ "id": 41, "bikes": 0, "free": 31}
,{ "id": 42, "bikes": 15, "free": 60}
,{ "id": 43, "bikes": 2, "free": 21}
,{ "id": 44, "bikes": 3, "free": 20}
,{ "id": 45, "bikes": 11, "free": 12}
,{ "id": 46, "bikes": 7, "free": 24}
,{ "id": 47, "bikes": 13, "free": 2}
,{ "id": 48, "bikes": 20, "free": 23}
,{ "id": 49, "bikes": 0, "free": 31}
,{ "id": 50, "bikes": 2, "free": 21}
,{ "id": 51, "bikes": 24, "free": 17}
,{ "id": 52, "bikes": 14, "free": 8}
,{ "id": 53, "bikes": 2, "free": 21}
,{ "id": 54, "bikes": 15, "free": 10}
,{ "id": 55, "bikes": 7, "free": 24}
,{ "id": 56, "bikes": 6, "free": 9}
,{ "id": 57, "bikes": 15, "free": 4}
,{ "id": 58, "bikes": 9, "free": 46}
,{ "id": 59, "bikes": 13, "free": 5}
,{ "id": 60, "bikes": 1, "free": 24}
,{ "id": 61, "bikes": 14, "free": 9}
,{ "id": 62, "bikes": 10, "free": 61}
,{ "id": 63, "bikes": 7, "free": 8}
,{ "id": 64, "bikes": 38, "free": 1}
,{ "id": 65, "bikes": 13, "free": 2}
,{ "id": 66, "bikes": 2, "free": 15}
,{ "id": 67, "bikes": 12, "free": 7}
,{ "id": 68, "bikes": 20, "free": 6}
,{ "id": 69, "bikes": 15, "free": 8}
,{ "id": 70, "bikes": 12, "free": 3}
,{ "id": 71, "bikes": 13, "free": 6}
,{ "id": 72, "bikes": 11, "free": 7}
,{ "id": 73, "bikes": 10, "free": 13}
,{ "id": 74, "bikes": 1, "free": 26}
,{ "id": 75, "bikes": 9, "free": 14}
,{ "id": 76, "bikes": 14, "free": 9}
,{ "id": 77, "bikes": 5, "free": 6}
,{ "id": 78, "bikes": 5, "free": 10}
,{ "id": 79, "bikes": 3, "free": 12}
,{ "id": 80, "bikes": 30, "free": 1}
,{ "id": 81, "bikes": 15, "free": 4}
,{ "id": 82, "bikes": 30, "free": 3}
,{ "id": 83, "bikes": 18, "free": 9}
,{ "id": 84, "bikes": 18, "free": 1}
,{ "id": 85, "bikes": 10, "free": 3}
,{ "id": 86, "bikes": 12, "free": 2}
,{ "id": 87, "bikes": 12, "free": 7}
,{ "id": 88, "bikes": 12, "free": 7}
,{ "id": 89, "bikes": 8, "free": 11}
,{ "id": 90, "bikes": 11, "free": 14}
,{ "id": 91, "bikes": 9, "free": 9}
,{ "id": 92, "bikes": 10, "free": 8}
,{ "id": 93, "bikes": 10, "free": 5}
,{ "id": 94, "bikes": 11, "free": 7}
,{ "id": 95, "bikes": 15, "free": 7}
,{ "id": 96, "bikes": 11, "free": 3}
,{ "id": 97, "bikes": 12, "free": 3}
,{ "id": 98, "bikes": 7, "free": 8}
,{ "id": 99, "bikes": 14, "free": 0}
,{ "id": 100, "bikes": 12, "free": 7}
,{ "id": 101, "bikes": 5, "free": 10}
,{ "id": 102, "bikes": 8, "free": 3}
,{ "id": 103, "bikes": 10, "free": 5}
,{ "id": 104, "bikes": 11, "free": 8}
,{ "id": 105, "bikes": 1, "free": 14}
,{ "id": 106, "bikes": 12, "free": 11}
,{ "id": 107, "bikes": 9, "free": 14}
,{ "id": 108, "bikes": 1, "free": 14}
,{ "id": 109, "bikes": 10, "free": 12}
,{ "id": 110, "bikes": 18, "free": 13}
,{ "id": 111, "bikes": 22, "free": 0}
,{ "id": 112, "bikes": 4, "free": 19}
,{ "id": 113, "bikes": 13, "free": 10}
,{ "id": 114, "bikes": 9, "free": 6}
,{ "id": 115, "bikes": 6, "free": 9}
,{ "id": 116, "bikes": 18, "free": 5}
,{ "id": 117, "bikes": 7, "free": 4}
,{ "id": 118, "bikes": 5, "free": 14}
,{ "id": 119, "bikes": 9, "free": 10}
,{ "id": 120, "bikes": 2, "free": 8}
,{ "id": 121, "bikes": 9, "free": 18}
,{ "id": 122, "bikes": 6, "free": 13}
,{ "id": 123, "bikes": 20, "free": 3}
,{ "id": 124, "bikes": 16, "free": 7}
,{ "id": 125, "bikes": 4, "free": 11}
,{ "id": 126, "bikes": 0, "free": 14}
,{ "id": 127, "bikes": 5, "free": 14}
,{ "id": 128, "bikes": 18, "free": 9}
,{ "id": 129, "bikes": 7, "free": 23}
,{ "id": 130, "bikes": 0, "free": 10}
,{ "id": 131, "bikes": 0, "free": 11}
,{ "id": 132, "bikes": 7, "free": 16}
,{ "id": 133, "bikes": 24, "free": 7}
,{ "id": 134, "bikes": 7, "free": 8}
,{ "id": 135, "bikes": 10, "free": 9}
,{ "id": 136, "bikes": 8, "free": 11}
,{ "id": 137, "bikes": 11, "free": 8}
,{ "id": 138, "bikes": 16, "free": 14}
,{ "id": 139, "bikes": 14, "free": 9}
,{ "id": 140, "bikes": 4, "free": 7}
,{ "id": 141, "bikes": 2, "free": 21}
,{ "id": 142, "bikes": 1, "free": 14}
,{ "id": 143, "bikes": 11, "free": 0}
,{ "id": 144, "bikes": 11, "free": 8}
,{ "id": 145, "bikes": 5, "free": 14}
,{ "id": 146, "bikes": 13, "free": 6}
,{ "id": 147, "bikes": 13, "free": 9}
,{ "id": 148, "bikes": 7, "free": 7}
,{ "id": 149, "bikes": 12, "free": 14}
,{ "id": 150, "bikes": 0, "free": 22}
,{ "id": 151, "bikes": 3, "free": 8}
,{ "id": 152, "bikes": 12, "free": 15}
,{ "id": 153, "bikes": 2, "free": 16}
,{ "id": 154, "bikes": 1, "free": 22}
,{ "id": 155, "bikes": 16, "free": 3}
,{ "id": 156, "bikes": 19, "free": 8}
,{ "id": 157, "bikes": 1, "free": 22}
,{ "id": 158, "bikes": 15, "free": 7}
,{ "id": 159, "bikes": 10, "free": 9}
,{ "id": 160, "bikes": 1, "free": 14}
,{ "id": 161, "bikes": 13, "free": 10}
,{ "id": 162, "bikes": 1, "free": 10}
,{ "id": 163, "bikes": 0, "free": 30}
,{ "id": 164, "bikes": 11, "free": 4}
,{ "id": 165, "bikes": 13, "free": 6}
,{ "id": 166, "bikes": 34, "free": 5}
,{ "id": 167, "bikes": 12, "free": 3}
,{ "id": 168, "bikes": 0, "free": 26}
,{ "id": 169, "bikes": 11, "free": 4}
,{ "id": 170, "bikes": 3, "free": 16}
,{ "id": 171, "bikes": 3, "free": 4}
,{ "id": 172, "bikes": 15, "free": 0}
,{ "id": 173, "bikes": 13, "free": 2}
,{ "id": 174, "bikes": 12, "free": 3}
,{ "id": 175, "bikes": 2, "free": 17}
,{ "id": 176, "bikes": 9, "free": 10}
,{ "id": 177, "bikes": 1, "free": 10}
,{ "id": 178, "bikes": 15, "free": 4}
,{ "id": 179, "bikes": 14, "free": 5}
,{ "id": 180, "bikes": 15, "free": 8}
,{ "id": 181, "bikes": 5, "free": 13}
,{ "id": 182, "bikes": 10, "free": 5}
,{ "id": 183, "bikes": 9, "free": 14}
,{ "id": 184, "bikes": 9, "free": 14}
,{ "id": 185, "bikes": 14, "free": 16}
,{ "id": 186, "bikes": 11, "free": 20}
,{ "id": 187, "bikes": 11, "free": 4}
,{ "id": 188, "bikes": 14, "free": 0}
,{ "id": 189, "bikes": 6, "free": 17}
,{ "id": 190, "bikes": 9, "free": 2}
,{ "id": 191, "bikes": 17, "free": 5}
,{ "id": 192, "bikes": 8, "free": 7}
,{ "id": 193, "bikes": 10, "free": 5}
,{ "id": 194, "bikes": 23, "free": 15}
,{ "id": 195, "bikes": 17, "free": 2}
,{ "id": 196, "bikes": 0, "free": 33}
,{ "id": 197, "bikes": 7, "free": 16}
,{ "id": 198, "bikes": 4, "free": 11}
,{ "id": 199, "bikes": 7, "free": 8}
,{ "id": 200, "bikes": 7, "free": 16}
,{ "id": 201, "bikes": 6, "free": 21}
,{ "id": 202, "bikes": 10, "free": 23}
,{ "id": 203, "bikes": 5, "free": 10}
,{ "id": 204, "bikes": 0, "free": 11}
,{ "id": 205, "bikes": 0, "free": 31}
,{ "id": 206, "bikes": 2, "free": 13}
,{ "id": 207, "bikes": 6, "free": 9}
,{ "id": 208, "bikes": 22, "free": 1}
,{ "id": 209, "bikes": 16, "free": 5}
,{ "id": 210, "bikes": 12, "free": 7}
,{ "id": 211, "bikes": 12, "free": 11}
,{ "id": 212, "bikes": 2, "free": 13}
,{ "id": 213, "bikes": 4, "free": 11}
,{ "id": 214, "bikes": 4, "free": 11}
,{ "id": 215, "bikes": 8, "free": 7}
,{ "id": 216, "bikes": 11, "free": 8}
,{ "id": 217, "bikes": 6, "free": 9}
,{ "id": 218, "bikes": 4, "free": 16}
,{ "id": 219, "bikes": 7, "free": 8}
,{ "id": 220, "bikes": 17, "free": 6}
,{ "id": 221, "bikes": 14, "free": 5}
,{ "id": 222, "bikes": 17, "free": 6}
,{ "id": 223, "bikes": 4, "free": 11}
,{ "id": 224, "bikes": 7, "free": 8}
,{ "id": 225, "bikes": 10, "free": 5}
,{ "id": 226, "bikes": 19, "free": 0}
,{ "id": 227, "bikes": 15, "free": 4}
,{ "id": 228, "bikes": 7, "free": 8}
,{ "id": 229, "bikes": 19, "free": 8}
,{ "id": 230, "bikes": 7, "free": 8}
,{ "id": 231, "bikes": 1, "free": 18}
,{ "id": 232, "bikes": 11, "free": 8}
,{ "id": 233, "bikes": 12, "free": 3}
,{ "id": 234, "bikes": 11, "free": 4}
,{ "id": 235, "bikes": 7, "free": 8}
,{ "id": 236, "bikes": 9, "free": 10}
,{ "id": 237, "bikes": 9, "free": 10}
,{ "id": 238, "bikes": 7, "free": 7}
,{ "id": 239, "bikes": 12, "free": 3}
,{ "id": 240, "bikes": 5, "free": 6}
,{ "id": 241, "bikes": 15, "free": 4}
,{ "id": 242, "bikes": 16, "free": 7}
,{ "id": 243, "bikes": 4, "free": 11}
,{ "id": 244, "bikes": 3, "free": 12}
,{ "id": 245, "bikes": 8, "free": 15}
,{ "id": 246, "bikes": 14, "free": 1}
,{ "id": 247, "bikes": 5, "free": 10}
,{ "id": 248, "bikes": 11, "free": 0}
,{ "id": 249, "bikes": 3, "free": 8}
,{ "id": 250, "bikes": 7, "free": 8}
,{ "id": 251, "bikes": 9, "free": 9}
,{ "id": 252, "bikes": 17, "free": 2}
,{ "id": 253, "bikes": 8, "free": 14}
,{ "id": 254, "bikes": 15, "free": 4}
,{ "id": 255, "bikes": 11, "free": 11}
,{ "id": 256, "bikes": 20, "free": 7}
,{ "id": 257, "bikes": 10, "free": 9}
,{ "id": 258, "bikes": 1, "free": 14}
,{ "id": 259, "bikes": 9, "free": 6}
,{ "id": 260, "bikes": 15, "free": 8}
,{ "id": 261, "bikes": 9, "free": 6}
,{ "id": 262, "bikes": 11, "free": 4}
,{ "id": 263, "bikes": 11, "free": 8}
,{ "id": 264, "bikes": 15, "free": 0}
,{ "id": 265, "bikes": 7, "free": 16}
,{ "id": 266, "bikes": 8, "free": 3}
,{ "id": 267, "bikes": 11, "free": 4}
,{ "id": 268, "bikes": 10, "free": 5}
,{ "id": 269, "bikes": 12, "free": 11}
,{ "id": 270, "bikes": 12, "free": 11}
,{ "id": 271, "bikes": 12, "free": 11}
,{ "id": 272, "bikes": 13, "free": 14}
,{ "id": 273, "bikes": 9, "free": 10}
,{ "id": 274, "bikes": 5, "free": 14}
,{ "id": 275, "bikes": 14, "free": 11}
,{ "id": 276, "bikes": 21, "free": 10}
,{ "id": 277, "bikes": 10, "free": 6}
,{ "id": 278, "bikes": 5, "free": 10}
,{ "id": 279, "bikes": 7, "free": 7}
,{ "id": 280, "bikes": 18, "free": 13}
,{ "id": 281, "bikes": 10, "free": 5}
,{ "id": 282, "bikes": 19, "free": 4}
,{ "id": 283, "bikes": 7, "free": 8}
,{ "id": 284, "bikes": 10, "free": 9}
,{ "id": 285, "bikes": 8, "free": 15}
,{ "id": 286, "bikes": 11, "free": 8}
,{ "id": 287, "bikes": 9, "free": 9}
,{ "id": 288, "bikes": 21, "free": 2}
,{ "id": 289, "bikes": 19, "free": 0}
,{ "id": 290, "bikes": 10, "free": 1}
,{ "id": 291, "bikes": 13, "free": 2}
,{ "id": 292, "bikes": 11, "free": 8}
,{ "id": 293, "bikes": 34, "free": 1}
,{ "id": 294, "bikes": 8, "free": 15}
,{ "id": 295, "bikes": 17, "free": 16}
,{ "id": 296, "bikes": 10, "free": 13}
,{ "id": 297, "bikes": 12, "free": 15}
,{ "id": 298, "bikes": 7, "free": 8}
,{ "id": 299, "bikes": 8, "free": 11}
,{ "id": 300, "bikes": 7, "free": 12}
,{ "id": 301, "bikes": 1, "free": 14}
,{ "id": 302, "bikes": 10, "free": 9}
,{ "id": 303, "bikes": 11, "free": 4}
,{ "id": 304, "bikes": 2, "free": 9}
,{ "id": 305, "bikes": 13, "free": 6}
,{ "id": 306, "bikes": 12, "free": 7}
,{ "id": 307, "bikes": 17, "free": 2}
,{ "id": 308, "bikes": 13, "free": 2}
,{ "id": 309, "bikes": 9, "free": 6}
,{ "id": 310, "bikes": 18, "free": 0}
,{ "id": 311, "bikes": 4, "free": 15}
,{ "id": 312, "bikes": 0, "free": 11}
,{ "id": 313, "bikes": 4, "free": 11}
,{ "id": 314, "bikes": 5, "free": 14}
,{ "id": 315, "bikes": 6, "free": 9}
,{ "id": 316, "bikes": 5, "free": 14}
,{ "id": 317, "bikes": 2, "free": 21}
,{ "id": 318, "bikes": 13, "free": 1}
,{ "id": 319, "bikes": 10, "free": 5}
,{ "id": 320, "bikes": 12, "free": 3}
,{ "id": 321, "bikes": 10, "free": 9}
,{ "id": 322, "bikes": 9, "free": 10}
,{ "id": 323, "bikes": 6, "free": 9}
,{ "id": 324, "bikes": 0, "free": 15}
,{ "id": 325, "bikes": 7, "free": 12}
,{ "id": 326, "bikes": 16, "free": 7}
,{ "id": 327, "bikes": 11, "free": 8}
,{ "id": 328, "bikes": 9, "free": 10}
,{ "id": 329, "bikes": 9, "free": 14}
,{ "id": 330, "bikes": 5, "free": 6}
,{ "id": 331, "bikes": 2, "free": 17}
,{ "id": 332, "bikes": 16, "free": 7}
,{ "id": 333, "bikes": 5, "free": 10}
,{ "id": 334, "bikes": 14, "free": 0}
,{ "id": 335, "bikes": 11, "free": 4}
,{ "id": 336, "bikes": 7, "free": 8}
,{ "id": 337, "bikes": 9, "free": 6}
,{ "id": 338, "bikes": 11, "free": 15}
,{ "id": 339, "bikes": 19, "free": 4}
,{ "id": 340, "bikes": 14, "free": 1}
,{ "id": 341, "bikes": 16, "free": 7}
,{ "id": 342, "bikes": 8, "free": 3}
,{ "id": 343, "bikes": 6, "free": 9}
,{ "id": 344, "bikes": 10, "free": 5}
,{ "id": 345, "bikes": 5, "free": 10}
,{ "id": 346, "bikes": 6, "free": 13}
,{ "id": 347, "bikes": 1, "free": 22}
,{ "id": 348, "bikes": 4, "free": 11}
,{ "id": 349, "bikes": 16, "free": 17}
,{ "id": 350, "bikes": 1, "free": 10}
,{ "id": 351, "bikes": 4, "free": 10}
,{ "id": 352, "bikes": 7, "free": 4}
,{ "id": 353, "bikes": 9, "free": 6}
,{ "id": 354, "bikes": 7, "free": 8}
,{ "id": 355, "bikes": 6, "free": 32}
,{ "id": 356, "bikes": 4, "free": 15}
,{ "id": 357, "bikes": 9, "free": 9}
,{ "id": 358, "bikes": 6, "free": 12}
,{ "id": 359, "bikes": 10, "free": 5}
,{ "id": 360, "bikes": 13, "free": 18}
,{ "id": 361, "bikes": 13, "free": 6}
,{ "id": 362, "bikes": 0, "free": 26}
,{ "id": 363, "bikes": 0, "free": 19}
,{ "id": 364, "bikes": 3, "free": 14}
,{ "id": 365, "bikes": 1, "free": 22}
,{ "id": 366, "bikes": 8, "free": 7}
,{ "id": 367, "bikes": 12, "free": 7}
,{ "id": 368, "bikes": 7, "free": 4}
,{ "id": 369, "bikes": 11, "free": 12}
,{ "id": 370, "bikes": 9, "free": 6}
,{ "id": 371, "bikes": 4, "free": 11}
,{ "id": 372, "bikes": 7, "free": 12}
,{ "id": 373, "bikes": 19, "free": 0}
,{ "id": 374, "bikes": 2, "free": 13}
,{ "id": 375, "bikes": 10, "free": 8}
,{ "id": 376, "bikes": 7, "free": 8}
,{ "id": 377, "bikes": 15, "free": 41}
,{ "id": 378, "bikes": 13, "free": 2}
,{ "id": 379, "bikes": 7, "free": 12}
,{ "id": 380, "bikes": 10, "free": 13}
,{ "id": 381, "bikes": 6, "free": 13}
,{ "id": 382, "bikes": 17, "free": 15}
,{ "id": 383, "bikes": 0, "free": 15}
,{ "id": 384, "bikes": 5, "free": 10}
,{ "id": 385, "bikes": 6, "free": 9}
,{ "id": 386, "bikes": 11, "free": 0}
,{ "id": 387, "bikes": 5, "free": 10}
,{ "id": 388, "bikes": 5, "free": 10}
,{ "id": 389, "bikes": 8, "free": 7}
,{ "id": 390, "bikes": 11, "free": 8}
,{ "id": 391, "bikes": 12, "free": 7}
,{ "id": 392, "bikes": 10, "free": 5}
,{ "id": 393, "bikes": 7, "free": 4}
,{ "id": 394, "bikes": 13, "free": 6}
,{ "id": 395, "bikes": 18, "free": 8}
,{ "id": 396, "bikes": 11, "free": 36}
,{ "id": 397, "bikes": 0, "free": 15}
,{ "id": 398, "bikes": 14, "free": 0}
,{ "id": 399, "bikes": 8, "free": 11}
,{ "id": 400, "bikes": 4, "free": 11}
,{ "id": 401, "bikes": 19, "free": 0}
,{ "id": 402, "bikes": 7, "free": 8}
,{ "id": 403, "bikes": 14, "free": 1}
,{ "id": 404, "bikes": 3, "free": 12}
,{ "id": 405, "bikes": 10, "free": 5}
,{ "id": 406, "bikes": 6, "free": 9}
,{ "id": 407, "bikes": 8, "free": 7}
,{ "id": 408, "bikes": 4, "free": 11}
,{ "id": 409, "bikes": 5, "free": 14}
,{ "id": 410, "bikes": 14, "free": 1}
,{ "id": 411, "bikes": 11, "free": 4}
,{ "id": 412, "bikes": 6, "free": 9}
,{ "id": 413, "bikes": 5, "free": 10}
,{ "id": 414, "bikes": 10, "free": 5}
,{ "id": 415, "bikes": 10, "free": 4}
,{ "id": 416, "bikes": 8, "free": 7}
,{ "id": 417, "bikes": 11, "free": 4}
,{ "id": 418, "bikes": 12, "free": 7}
,{ "id": 419, "bikes": 12, "free": 7}
,{ "id": 420, "bikes": 13, "free": 2}
,{ "id": 421, "bikes": 6, "free": 8}
,{ "id": 422, "bikes": 11, "free": 8}
,{ "id": 423, "bikes": 17, "free": 2}
,{ "id": 424, "bikes": 11, "free": 4}
,{ "id": 425, "bikes": 6, "free": 9}
,{ "id": 426, "bikes": 2, "free": 13}
,{ "id": 427, "bikes": 18, "free": 1}
,{ "id": 428, "bikes": 4, "free": 11}
,{ "id": 429, "bikes": 9, "free": 6}
,{ "id": 430, "bikes": 12, "free": 3}
,{ "id": 431, "bikes": 10, "free": 5}
,{ "id": 432, "bikes": 4, "free": 10}
,{ "id": 433, "bikes": 10, "free": 9}
,{ "id": 434, "bikes": 16, "free": 3}
,{ "id": 435, "bikes": 6, "free": 9}
,{ "id": 436, "bikes": 8, "free": 15}
,{ "id": 437, "bikes": 12, "free": 3}
,{ "id": 438, "bikes": 7, "free": 8}
,{ "id": 439, "bikes": 8, "free": 6}
,{ "id": 440, "bikes": 10, "free": 5}
,{ "id": 441, "bikes": 3, "free": 8}
,{ "id": 442, "bikes": 4, "free": 7}
,{ "id": 443, "bikes": 10, "free": 5}
,{ "id": 444, "bikes": 7, "free": 8}

]
}